pyimgur/__init__.py
pyimgur/basic_objects.py
pyimgur/conversion.py
pyimgur/exceptions.py
pyimgur/image.py
pyimgur/objects.py
pyimgur/request.py
pyimgur-0.8.1.dist-info/METADATA
pyimgur-0.8.1.dist-info/WHEEL
pyimgur-0.8.1.dist-info/licenses/COPYING
pyimgur-0.8.1.dist-info/RECORD
