Metadata-Version: 2.4
Name: pyimgur
Version: 0.8.1
Summary: The easy way of using Imgur
Project-URL: Homepage, https://github.com/Damgaard/PyImgur
Project-URL: Documentation, https://pyimgur.readthedocs.org
Author-email: Andreas Damgaard Pedersen <andreas.damgaard.pedersen@gmail.com>
License-File: COPYING
Keywords: PyImgur,api,imgur,wrapper
Classifier: Development Status :: 4 - Beta
Classifier: Environment :: Console
Classifier: Intended Audience :: Developers
Classifier: License :: OSI Approved :: GNU General Public License v3 (GPLv3)
Classifier: Natural Language :: English
Classifier: Operating System :: OS Independent
Classifier: Programming Language :: Python :: 3
Classifier: Topic :: Utilities
Requires-Python: >=3.9
Requires-Dist: requests
